jenkenv/__init__.py
jenkenv/jenkinsfile-runner/.git
jenkenv/jenkinsfile-runner/.gitignore
jenkenv/jenkinsfile-runner/DOCKER.md
jenkenv/jenkinsfile-runner/Dockerfile
jenkenv/jenkinsfile-runner/IMPLEMENTATION.md
jenkenv/jenkinsfile-runner/Jenkinsfile
jenkenv/jenkinsfile-runner/README.md
jenkenv/jenkinsfile-runner/plugins.txt
jenkenv/jenkinsfile-runner/pom.xml
jenkenv/jenkinsfile-runner/sample.nps
jenkenv/jenkinsfile-runner/app/pom.xml
jenkenv/jenkinsfile-runner/app/target/jenkinsfile-runner.jar
jenkenv/jenkinsfile-runner/app/target/appassembler/bin/jenkinsfile-runner
jenkenv/jenkinsfile-runner/app/target/appassembler/bin/jenkinsfile-runner.bat
jenkenv/jenkinsfile-runner/app/target/appassembler/repo/antlr/antlr/2.7.6/antlr-2.7.6.jar
jenkenv/jenkinsfile-runner/app/target/appassembler/repo/aopalliance/aopalliance/1.0/aopalliance-1.0.jar
jenkenv/jenkinsfile-runner/app/target/appassembler/repo/args4j/args4j/2.33/args4j-2.33.jar
jenkenv/jenkinsfile-runner/app/target/appassembler/repo/com/cloudbees/diff4j/1.2/diff4j-1.2.jar
jenkenv/jenkinsfile-runner/app/target/appassembler/repo/com/cloudbees/groovy-cps/1.20/groovy-cps-1.20.jar
jenkenv/jenkinsfile-runner/app/target/appassembler/repo/com/github/jnr/jffi/1.2.15/jffi-1.2.15-native.jar
jenkenv/jenkinsfile-runner/app/target/appassembler/repo/com/github/jnr/jffi/1.2.15/jffi-1.2.15.jar
jenkenv/jenkinsfile-runner/app/target/appassembler/repo/com/github/jnr/jnr-constants/0.9.8/jnr-constants-0.9.8.jar
jenkenv/jenkinsfile-runner/app/target/appassembler/repo/com/github/jnr/jnr-ffi/2.1.4/jnr-ffi-2.1.4.jar
jenkenv/jenkinsfile-runner/app/target/appassembler/repo/com/github/jnr/jnr-posix/3.0.41/jnr-posix-3.0.41.jar
jenkenv/jenkinsfile-runner/app/target/appassembler/repo/com/github/jnr/jnr-x86asm/1.0.2/jnr-x86asm-1.0.2.jar
jenkenv/jenkinsfile-runner/app/target/appassembler/repo/com/github/stephenc/findbugs/findbugs-annotations/1.3.9-1/findbugs-annotations-1.3.9-1.jar
jenkenv-0.0.3.dist-info/METADATA
jenkenv-0.0.3.dist-info/RECORD
jenkenv-0.0.3.dist-info/WHEEL
jenkenv-0.0.3.dist-info/entry_points.txt
jenkenv-0.0.3.dist-info/top_level.txt
