Metadata-Version: 2.1
Name: jenkenv
Version: 0.0.3
Summary: UNKNOWN
Home-page: https://github.com/jamesalbert/jenkenv
Author: jamesrobertalbert@gmail.com
Author-email: UNKNOWN
License: UNKNOWN
Platform: UNKNOWN
Classifier: Programming Language :: Python :: 3
Classifier: License :: OSI Approved :: GNU General Public License (GPL)
Requires-Dist: docopt
